Metadata-Version: 1.1
Name: gat-runner
Version: 0.0.2
Summary: GAT Runner
Home-page: https://github.com/gatournament/gat-runner
Author: gatournament
Author-email: info@gatournament.com
License: MIT
Keywords: gat game algorithms tournament
Platform: UNKNOWN
Classifier: Operating System :: OS Independent
Classifier: Topic :: Software Development
